crispy_forms_govuk/__init__.py
crispy_forms_govuk/forms.py
crispy_forms_govuk/layout/__init__.py
crispy_forms_govuk/layout/buttons.py
crispy_forms_govuk/layout/fields.py
crispy_forms_govuk/settings.py
crispy_forms_govuk/static/js/all.js
crispy_forms_govuk/templates/govuk/display_form.html
crispy_forms_govuk/templates/govuk/display_formset.html
crispy_forms_govuk/templates/govuk/errors.html
crispy_forms_govuk/templates/govuk/errors_formset.html
crispy_forms_govuk/templates/govuk/field.html
crispy_forms_govuk/templates/govuk/inputs.html
crispy_forms_govuk/templates/govuk/layout/basebutton.html
crispy_forms_govuk/templates/govuk/layout/baseinput.html
crispy_forms_govuk/templates/govuk/layout/buttonholder.html
crispy_forms_govuk/templates/govuk/layout/checkbox.html
crispy_forms_govuk/templates/govuk/layout/checkboxmultiple.html
crispy_forms_govuk/templates/govuk/layout/div.html
crispy_forms_govuk/templates/govuk/layout/link.html
crispy_forms_govuk/templates/govuk/layout/radioselect.html
crispy_forms_govuk/templates/govuk/layout/select.html
crispy_forms_govuk/templates/govuk/radio_accordion.html
crispy_forms_govuk/templates/govuk/radio_accordion_group.html
crispy_forms_govuk/templates/govuk/snippets/field_errors.html
crispy_forms_govuk/templates/govuk/snippets/field_hint.html
crispy_forms_govuk/templates/govuk/snippets/field_label.html
crispy_forms_govuk/templates/govuk/snippets/field_legend.html
crispy_forms_govuk/templates/govuk/uni_form.html
crispy_forms_govuk/templates/govuk/whole_uni_form.html
crispy_forms_govuk/templates/govuk/whole_uni_formset.html
crispy_forms_govuk/templates/govuk/widget.html
crispy_forms_govuk/templatetags/__init__.py
crispy_forms_govuk/templatetags/crispy_forms_govuk_tags.py
crispy_forms_govuk-0.2.0.dist-info/WHEEL
crispy_forms_govuk-0.2.0.dist-info/METADATA
crispy_forms_govuk-0.2.0.dist-info/RECORD
