Metadata-Version: 2.1
Name: crispy-forms-govuk
Version: 0.2.0
Summary: 
License: MIT
Author: Your Name
Author-email: you@example.com
Requires-Python: >=3.9,<4.0
Classifier: License :: OSI Approved :: MIT License
Classifier: Programming Language :: Python :: 3
Classifier: Programming Language :: Python :: 3.10
Classifier: Programming Language :: Python :: 3.9
Requires-Dist: django (>=3.1.0,<4.0.0)
Requires-Dist: django-crispy-forms (>=1.9.0,<1.10.0)
